MANIFEST.in
README.md
requirements.txt
setup.py
customers/__init__.py
customers/admin.py
customers/forms.py
customers/models.py
customers/urls.py
customers/views.py
customers/locale/uk/LC_MESSAGES/django.mo
customers/locale/uk/LC_MESSAGES/django.po
customers/migrations/0001_initial.py
customers/migrations/0002_customer_discount.py
customers/migrations/__init__.py
customers/templates/customers/actions_cell.html
customers/templates/customers/detail.html
customers/templates/customers/sale_count_cell.html
django_mp_invoices.egg-info/PKG-INFO
django_mp_invoices.egg-info/SOURCES.txt
django_mp_invoices.egg-info/dependency_links.txt
django_mp_invoices.egg-info/requires.txt
django_mp_invoices.egg-info/top_level.txt
invoices/__init__.py
invoices/actions.py
invoices/admin.py
invoices/conf.py
invoices/forms.py
invoices/middleware.py
invoices/models.py
invoices/service.py
invoices/urls.py
invoices/views.py
invoices/locale/ru/LC_MESSAGES/django.mo
invoices/locale/ru/LC_MESSAGES/django.po
invoices/locale/uk/LC_MESSAGES/django.mo
invoices/locale/uk/LC_MESSAGES/django.po
invoices/management/__init__.py
invoices/management/commands/__init__.py
invoices/management/commands/sync_arrivals.py
invoices/migrations/0001_initial.py
invoices/migrations/0002_invoice_creator.py
invoices/migrations/0003_change_qty_to_float.py
invoices/migrations/0004_auto_20220115_1231.py
invoices/migrations/0005_arrival_supplier.py
invoices/migrations/0006_invoice_currency.py
invoices/migrations/0007_currency_rate.py
invoices/migrations/0008_totals.py
invoices/migrations/0009_auto_20221205_1712.py
invoices/migrations/__init__.py
invoices/static/invoices/CategoryTree.js
invoices/static/invoices/ContactChoiceField.js
invoices/static/invoices/CurrencyRateInput.js
invoices/static/invoices/CurrencySelect.js
invoices/static/invoices/InvoiceList.js
invoices/static/invoices/InvoiceTotal.js
invoices/static/invoices/SelectProductList.js
invoices/static/invoices/SelectServiceItemList.js
invoices/static/invoices/invoices.css
invoices/static/invoices/jquery.scannerdetection.js
invoices/templates/accounting.html
invoices/templates/invoices/contact-select.html
invoices/templates/invoices/history.html
