Metadata-Version: 2.1
Name: django-mp-invoices
Version: 1.1.5
Summary: Django invoices apps
Home-page: https://github.com/pmaigutyak/mp-invoices
Author: Paul Maigutyak
Author-email: pmaigutyak@gmail.com
License: MIT
Download-URL: https://github.com/pmaigutyak/mp-invoices/archive/1.1.5.tar.gz
Platform: UNKNOWN
